audiofilearranger/__init__.py
audiofilearranger/audiofilearranger.py
audiofilearranger-0.1.0.dist-info/DESCRIPTION.rst
audiofilearranger-0.1.0.dist-info/METADATA
audiofilearranger-0.1.0.dist-info/RECORD
audiofilearranger-0.1.0.dist-info/WHEEL
audiofilearranger-0.1.0.dist-info/entry_points.txt
audiofilearranger-0.1.0.dist-info/metadata.json
audiofilearranger-0.1.0.dist-info/top_level.txt
